home_media_organizer/__init__.py
home_media_organizer/classify.py
home_media_organizer/cleanup.py
home_media_organizer/cli.py
home_media_organizer/compare.py
home_media_organizer/config.py
home_media_organizer/dedup.py
home_media_organizer/home_media_organizer.py
home_media_organizer/list.py
home_media_organizer/media_file.py
home_media_organizer/organize.py
home_media_organizer/py.typed
home_media_organizer/remove_tags.py
home_media_organizer/rename.py
home_media_organizer/set_exif.py
home_media_organizer/set_tags.py
home_media_organizer/shift_exif.py
home_media_organizer/show_exif.py
home_media_organizer/show_tags.py
home_media_organizer/utils.py
home_media_organizer/validate.py
home_media_organizer-0.3.7.dist-info/LICENSE.rst
home_media_organizer-0.3.7.dist-info/METADATA
home_media_organizer-0.3.7.dist-info/WHEEL
home_media_organizer-0.3.7.dist-info/entry_points.txt
home_media_organizer-0.3.7.dist-info/RECORD
