Metadata-Version: 2.3
Name: home-media-organizer
Version: 0.3.7
Summary: A Swiss Army Knife for your home media library.
Keywords: home-media-organizer
Author: Bo Peng
Author-email: ben.bob@gmail.com
Requires-Python: >=3.10,<3.13
Classifier: Development Status :: 2 - Pre-Alpha
Classifier: Intended Audience :: Developers
Classifier: License :: OSI Approved :: MIT License
Classifier: Natural Language :: English
Classifier: Programming Language :: Python :: 3
Classifier: Programming Language :: Python :: 3.10
Classifier: Programming Language :: Python :: 3.11
Classifier: Programming Language :: Python :: 3.12
Requires-Dist: Augmentor (>=0.2.12,<0.3.0)
Requires-Dist: deepface (>=0.0.93,<0.0.94)
Requires-Dist: diskcache (>=5.6.3,<6.0.0)
Requires-Dist: ffmpeg-python (>=0.2.0,<0.3.0)
Requires-Dist: inflect (>=7.5.0,<8.0.0)
Requires-Dist: ml-dtypes (>=0.4.1,<0.5.0)
Requires-Dist: nudenet (>=3.4.2,<4.0.0)
Requires-Dist: numpy (>=2.0.2,<3.0.0)
Requires-Dist: pillow (>=11.1.0,<12.0.0)
Requires-Dist: pyexiftool (>=0.5.6,<0.6.0)
Requires-Dist: pyparsing (>=3.2.1,<4.0.0)
Requires-Dist: rich (==13.9.4)
Requires-Dist: tf-keras (>=2.18.0,<3.0.0)
Requires-Dist: tomli (==2.2.1) ; python_version < "3.11"
Requires-Dist: tqdm (>=4.67.1,<5.0.0)
Project-URL: Bug Tracker, https://github.com/BoPeng/home-media-organizer/issues
Project-URL: Documentation, https://home-media-organizer.readthedocs.io
Project-URL: Homepage, https://github.com/BoPeng/home-media-organizer
Project-URL: Repository, https://github.com/BoPeng/home-media-organizer
